tap_auth0/__init__.py
tap_auth0-0.0.1.dist-info/LICENSE
tap_auth0-0.0.1.dist-info/METADATA
tap_auth0-0.0.1.dist-info/WHEEL
tap_auth0-0.0.1.dist-info/entry_points.txt
tap_auth0-0.0.1.dist-info/top_level.txt
tap_auth0-0.0.1.dist-info/RECORD
