Metadata-Version: 2.1
Name: tap-auth0
Version: 0.0.1
Summary: Singer.io tap for extracting data from the Auth0 Management API v2
Home-page: http://singer.io
Author: Jean-Nicholas Hould (jeannicholashould.com)
Author-email: UNKNOWN
License: UNKNOWN
Platform: UNKNOWN
Classifier: Programming Language :: Python :: 3 :: Only
Requires-Dist: auth0-python (==3.9.1)
Requires-Dist: singer-python (==2.1.4)
